examples/__init__.py
examples/example.py
examples/setuptools.py
ideas/stubble.py
reahl/stubble/__init__.py
reahl/stubble/easteregg.py
reahl/stubble/intercept.py
reahl/stubble/stub.py
reahl/stubble_dev/__init__.py
reahl/stubble_dev/test_basicstubbing.py
reahl/stubble_dev/test_delegation.py
reahl/stubble_dev/test_easteregg.py
reahl/stubble_dev/test_impostoring.py
reahl/stubble_dev/test_instancevariables.py
reahl/stubble_dev/test_intercept.py
reahl_stubble-7.0.3.dist-info/LICENSE
reahl_stubble-7.0.3.dist-info/METADATA
reahl_stubble-7.0.3.dist-info/WHEEL
reahl_stubble-7.0.3.dist-info/reahl-component.toml
reahl_stubble-7.0.3.dist-info/top_level.txt
reahl_stubble-7.0.3.dist-info/RECORD
